nextmv/__about__.py
nextmv/__entrypoint__.py
nextmv/__init__.py
nextmv/_serialization.py
nextmv/base_model.py
nextmv/deprecated.py
nextmv/input.py
nextmv/logger.py
nextmv/manifest.py
nextmv/model.py
nextmv/options.py
nextmv/output.py
nextmv/polling.py
nextmv/run.py
nextmv/safe.py
nextmv/status.py
nextmv/cli/__init__.py
nextmv/cli/error.py
nextmv/cli/main.py
nextmv/cli/options.py
nextmv/cli/version.py
nextmv/cli/community/__init__.py
nextmv/cli/community/clone.py
nextmv/cli/community/community.py
nextmv/cli/community/list.py
nextmv/cli/configuration/__init__.py
nextmv/cli/configuration/config.py
nextmv/cli/configuration/configuration.py
nextmv/cli/configuration/create.py
nextmv/cli/configuration/delete.py
nextmv/cli/configuration/list.py
nextmv/cloud/__init__.py
nextmv/cloud/acceptance_test.py
nextmv/cloud/account.py
nextmv/cloud/application.py
nextmv/cloud/assets.py
nextmv/cloud/batch_experiment.py
nextmv/cloud/client.py
nextmv/cloud/ensemble.py
nextmv/cloud/input_set.py
nextmv/cloud/instance.py
nextmv/cloud/integration.py
nextmv/cloud/package.py
nextmv/cloud/scenario.py
nextmv/cloud/secrets.py
nextmv/cloud/url.py
nextmv/cloud/version.py
nextmv/default_app/.gitignore
nextmv/default_app/README.md
nextmv/default_app/app.yaml
nextmv/default_app/input.json
nextmv/default_app/main.py
nextmv/default_app/requirements.txt
nextmv/default_app/src/__init__.py
nextmv/default_app/src/visuals.py
nextmv/local/__init__.py
nextmv/local/application.py
nextmv/local/executor.py
nextmv/local/geojson_handler.py
nextmv/local/local.py
nextmv/local/plotly_handler.py
nextmv/local/runner.py
nextmv-0.40.0.dist-info/METADATA
nextmv-0.40.0.dist-info/WHEEL
nextmv-0.40.0.dist-info/licenses/LICENSE
nextmv-0.40.0.dist-info/RECORD
