Metadata-Version: 2.4
Name: nextmv
Version: 0.40.0
Summary: The all-purpose Python SDK for Nextmv
Project-URL: Homepage, https://www.nextmv.io
Project-URL: Documentation, https://nextmv-py.docs.nextmv.io/en/latest/nextmv/
Project-URL: Repository, https://github.com/nextmv-io/nextmv-py
Author-email: Nextmv <tech@nextmv.io>
Maintainer-email: Nextmv <tech@nextmv.io>
License:                                  Apache License
License-File: LICENSE
Keywords: decision engineering,decision science,decisions,nextmv,operations research,optimization,shift scheduling,solver,vehicle routing problem
Classifier: License :: OSI Approved :: Apache Software License
Classifier: Operating System :: OS Independent
Classifier: Programming Language :: Python :: 3
Classifier: Programming Language :: Python :: 3.10
Classifier: Programming Language :: Python :: 3.11
Classifier: Programming Language :: Python :: 3.12
Classifier: Programming Language :: Python :: 3.13
Requires-Python: >=3.10
Requires-Dist: pydantic>=2.5.2
Requires-Dist: pyyaml>=6.0.1
Requires-Dist: requests>=2.31.0
Requires-Dist: typer>=0.20.1
Requires-Dist: urllib3>=2.1.0
Provides-Extra: all
Requires-Dist: folium>=0.20.0; extra == 'all'
Requires-Dist: plotly>=6.0.1; extra == 'all'
Provides-Extra: dev
Requires-Dist: build>=1.0.3; extra == 'dev'
Requires-Dist: folium>=0.20.0; extra == 'dev'
Requires-Dist: mlflow>=2.19.0; extra == 'dev'
Requires-Dist: nextroute>=1.11.1; extra == 'dev'
Requires-Dist: openpyxl>=3.1.5; extra == 'dev'
Requires-Dist: pandas>=2.2.3; extra == 'dev'
Requires-Dist: plotly>=6.0.1; extra == 'dev'
Requires-Dist: pydantic>=2.5.2; extra == 'dev'
Requires-Dist: pyyaml>=6.0.1; extra == 'dev'
Requires-Dist: requests>=2.31.0; extra == 'dev'
Requires-Dist: ruff>=0.1.7; extra == 'dev'
Requires-Dist: twine>=4.0.2; extra == 'dev'
Requires-Dist: urllib3>=2.1.0; extra == 'dev'
Provides-Extra: notebook
Requires-Dist: mlflow>=2.19.0; extra == 'notebook'
